__init__.py
som/__init__.py
som/som.py
scikit_learn_som-0.0.3.dist-info/METADATA
scikit_learn_som-0.0.3.dist-info/WHEEL
scikit_learn_som-0.0.3.dist-info/top_level.txt
scikit_learn_som-0.0.3.dist-info/RECORD
