Metadata-Version: 2.4
Name: scikit-learn-som
Version: 0.0.3
Requires-Python: >=3.12
Requires-Dist: scikit-learn>=1.6.1
